LICENSE
MANIFEST.in
Pipfile
Pipfile.lock
README.md
pytest.ini
requirements.txt
setup.cfg
setup.py
src/pywbs/__init__.py
src/pywbs/tree.py
src/pywbs.egg-info/PKG-INFO
src/pywbs.egg-info/SOURCES.txt
src/pywbs.egg-info/dependency_links.txt
src/pywbs.egg-info/not-zip-safe
src/pywbs.egg-info/top_level.txt