Metadata-Version: 1.1
Name: pywbs
Version: 0.2
Summary: Work Breakdown structures for project management
Home-page: https://github.com/GigiusB/pywbs
Author: Giovanni Bronzini
Author-email: g.bronzini@gmail.com
License: BSD 3-Clause
Keywords: date,util
Platform: UNKNOWN
Classifier: Development Status :: 3 - Alpha
Classifier: License :: OSI Approved :: BSD License
Classifier: Natural Language :: English
Classifier: Programming Language :: Python :: 3.6
